{"nodes": [{"id": "c_users_keanghour_documents_github_fnode_rcon_core_xray_app_dispatcher_linkmanager_go", "label": "linkmanager.go", "file_type": "code", "source_file": "C:\\Users\\Keanghour\\Documents\\GitHub\\FNode\\Rcon\\core\\xray\\app\\dispatcher\\linkmanager.go", "source_location": "L1"}, {"id": "dispatcher_managedwriter", "label": "ManagedWriter", "file_type": "code", "source_file": "C:\\Users\\Keanghour\\Documents\\GitHub\\FNode\\Rcon\\core\\xray\\app\\dispatcher\\linkmanager.go", "source_location": "L10"}, {"id": "dispatcher_managedwriter_writemultibuffer", "label": ".WriteMultiBuffer()", "file_type": "code", "source_file": "C:\\Users\\Keanghour\\Documents\\GitHub\\FNode\\Rcon\\core\\xray\\app\\dispatcher\\linkmanager.go", "source_location": "L15"}, {"id": "dispatcher_managedwriter_close", "label": ".Close()", "file_type": "code", "source_file": "C:\\Users\\Keanghour\\Documents\\GitHub\\FNode\\Rcon\\core\\xray\\app\\dispatcher\\linkmanager.go", "source_location": "L19"}, {"id": "dispatcher_linkmanager", "label": "LinkManager", "file_type": "code", "source_file": "C:\\Users\\Keanghour\\Documents\\GitHub\\FNode\\Rcon\\core\\xray\\app\\dispatcher\\linkmanager.go", "source_location": "L24"}, {"id": "dispatcher_linkmanager_addlink", "label": ".AddLink()", "file_type": "code", "source_file": "C:\\Users\\Keanghour\\Documents\\GitHub\\FNode\\Rcon\\core\\xray\\app\\dispatcher\\linkmanager.go", "source_location": "L29"}, {"id": "dispatcher_linkmanager_removewriter", "label": ".RemoveWriter()", "file_type": "code", "source_file": "C:\\Users\\Keanghour\\Documents\\GitHub\\FNode\\Rcon\\core\\xray\\app\\dispatcher\\linkmanager.go", "source_location": "L35"}, {"id": "dispatcher_linkmanager_closeall", "label": ".CloseAll()", "file_type": "code", "source_file": "C:\\Users\\Keanghour\\Documents\\GitHub\\FNode\\Rcon\\core\\xray\\app\\dispatcher\\linkmanager.go", "source_location": "L41"}], "edges": [{"source": "c_users_keanghour_documents_github_fnode_rcon_core_xray_app_dispatcher_linkmanager_go", "target": "go_pkg_sync", "relation": "imports_from", "confidence": "EXTRACTED", "source_file": "C:\\Users\\Keanghour\\Documents\\GitHub\\FNode\\Rcon\\core\\xray\\app\\dispatcher\\linkmanager.go", "source_location": "L4", "weight": 1.0, "context": "import"}, {"source": "c_users_keanghour_documents_github_fnode_rcon_core_xray_app_dispatcher_linkmanager_go", "target": "go_pkg_github_com_xtls_xray_core_common", "relation": "imports_from", "confidence": "EXTRACTED", "source_file": "C:\\Users\\Keanghour\\Documents\\GitHub\\FNode\\Rcon\\core\\xray\\app\\dispatcher\\linkmanager.go", "source_location": "L6", "weight": 1.0, "context": "import"}, {"source": "c_users_keanghour_documents_github_fnode_rcon_core_xray_app_dispatcher_linkmanager_go", "target": "go_pkg_github_com_xtls_xray_core_common_buf", "relation": "imports_from", "confidence": "EXTRACTED", "source_file": "C:\\Users\\Keanghour\\Documents\\GitHub\\FNode\\Rcon\\core\\xray\\app\\dispatcher\\linkmanager.go", "source_location": "L7", "weight": 1.0, "context": "import"}, {"source": "c_users_keanghour_documents_github_fnode_rcon_core_xray_app_dispatcher_linkmanager_go", "target": "dispatcher_managedwriter", "relation": "contains", "confidence": "EXTRACTED", "source_file": "C:\\Users\\Keanghour\\Documents\\GitHub\\FNode\\Rcon\\core\\xray\\app\\dispatcher\\linkmanager.go", "source_location": "L10", "weight": 1.0}, {"source": "dispatcher_managedwriter", "target": "dispatcher_managedwriter_writemultibuffer", "relation": "method", "confidence": "EXTRACTED", "source_file": "C:\\Users\\Keanghour\\Documents\\GitHub\\FNode\\Rcon\\core\\xray\\app\\dispatcher\\linkmanager.go", "source_location": "L15", "weight": 1.0}, {"source": "dispatcher_managedwriter", "target": "dispatcher_managedwriter_close", "relation": "method", "confidence": "EXTRACTED", "source_file": "C:\\Users\\Keanghour\\Documents\\GitHub\\FNode\\Rcon\\core\\xray\\app\\dispatcher\\linkmanager.go", "source_location": "L19", "weight": 1.0}, {"source": "c_users_keanghour_documents_github_fnode_rcon_core_xray_app_dispatcher_linkmanager_go", "target": "dispatcher_linkmanager", "relation": "contains", "confidence": "EXTRACTED", "source_file": "C:\\Users\\Keanghour\\Documents\\GitHub\\FNode\\Rcon\\core\\xray\\app\\dispatcher\\linkmanager.go", "source_location": "L24", "weight": 1.0}, {"source": "dispatcher_linkmanager", "target": "dispatcher_linkmanager_addlink", "relation": "method", "confidence": "EXTRACTED", "source_file": "C:\\Users\\Keanghour\\Documents\\GitHub\\FNode\\Rcon\\core\\xray\\app\\dispatcher\\linkmanager.go", "source_location": "L29", "weight": 1.0}, {"source": "dispatcher_linkmanager", "target": "dispatcher_linkmanager_removewriter", "relation": "method", "confidence": "EXTRACTED", "source_file": "C:\\Users\\Keanghour\\Documents\\GitHub\\FNode\\Rcon\\core\\xray\\app\\dispatcher\\linkmanager.go", "source_location": "L35", "weight": 1.0}, {"source": "dispatcher_linkmanager", "target": "dispatcher_linkmanager_closeall", "relation": "method", "confidence": "EXTRACTED", "source_file": "C:\\Users\\Keanghour\\Documents\\GitHub\\FNode\\Rcon\\core\\xray\\app\\dispatcher\\linkmanager.go", "source_location": "L41", "weight": 1.0}, {"source": "dispatcher_managedwriter_close", "target": "dispatcher_linkmanager_removewriter", "relation": "calls", "context": "call", "confidence": "EXTRACTED", "source_file": "C:\\Users\\Keanghour\\Documents\\GitHub\\FNode\\Rcon\\core\\xray\\app\\dispatcher\\linkmanager.go", "source_location": "L20", "weight": 1.0}, {"source": "dispatcher_linkmanager_closeall", "target": "dispatcher_managedwriter_close", "relation": "calls", "context": "call", "confidence": "EXTRACTED", "source_file": "C:\\Users\\Keanghour\\Documents\\GitHub\\FNode\\Rcon\\core\\xray\\app\\dispatcher\\linkmanager.go", "source_location": "L43", "weight": 1.0}], "raw_calls": [{"caller_nid": "dispatcher_managedwriter_writemultibuffer", "callee": "WriteMultiBuffer", "is_member_call": true, "source_file": "C:\\Users\\Keanghour\\Documents\\GitHub\\FNode\\Rcon\\core\\xray\\app\\dispatcher\\linkmanager.go", "source_location": "L16"}, {"caller_nid": "dispatcher_managedwriter_close", "callee": "Close", "is_member_call": false, "source_file": "C:\\Users\\Keanghour\\Documents\\GitHub\\FNode\\Rcon\\core\\xray\\app\\dispatcher\\linkmanager.go", "source_location": "L21"}, {"caller_nid": "dispatcher_linkmanager_addlink", "callee": "Lock", "is_member_call": true, "source_file": "C:\\Users\\Keanghour\\Documents\\GitHub\\FNode\\Rcon\\core\\xray\\app\\dispatcher\\linkmanager.go", "source_location": "L30"}, {"caller_nid": "dispatcher_linkmanager_addlink", "callee": "Unlock", "is_member_call": true, "source_file": "C:\\Users\\Keanghour\\Documents\\GitHub\\FNode\\Rcon\\core\\xray\\app\\dispatcher\\linkmanager.go", "source_location": "L31"}, {"caller_nid": "dispatcher_linkmanager_removewriter", "callee": "Lock", "is_member_call": true, "source_file": "C:\\Users\\Keanghour\\Documents\\GitHub\\FNode\\Rcon\\core\\xray\\app\\dispatcher\\linkmanager.go", "source_location": "L36"}, {"caller_nid": "dispatcher_linkmanager_removewriter", "callee": "Unlock", "is_member_call": true, "source_file": "C:\\Users\\Keanghour\\Documents\\GitHub\\FNode\\Rcon\\core\\xray\\app\\dispatcher\\linkmanager.go", "source_location": "L37"}, {"caller_nid": "dispatcher_linkmanager_removewriter", "callee": "delete", "is_member_call": false, "source_file": "C:\\Users\\Keanghour\\Documents\\GitHub\\FNode\\Rcon\\core\\xray\\app\\dispatcher\\linkmanager.go", "source_location": "L38"}, {"caller_nid": "dispatcher_linkmanager_closeall", "callee": "Interrupt", "is_member_call": false, "source_file": "C:\\Users\\Keanghour\\Documents\\GitHub\\FNode\\Rcon\\core\\xray\\app\\dispatcher\\linkmanager.go", "source_location": "L44"}]}