{"nodes": [{"id": "c_users_keanghour_documents_github_fnode_rcon_deps_xray_core_infra_conf_geodata_go", "label": "geodata.go", "file_type": "code", "source_file": "C:\\Users\\Keanghour\\Documents\\GitHub\\FNode\\Rcon\\deps\\xray-core\\infra\\conf\\geodata.go", "source_location": "L1"}, {"id": "conf_geodataassetconfig", "label": "GeodataAssetConfig", "file_type": "code", "source_file": "C:\\Users\\Keanghour\\Documents\\GitHub\\FNode\\Rcon\\deps\\xray-core\\infra\\conf\\geodata.go", "source_location": "L13"}, {"id": "conf_geodataassetconfig_build", "label": ".Build()", "file_type": "code", "source_file": "C:\\Users\\Keanghour\\Documents\\GitHub\\FNode\\Rcon\\deps\\xray-core\\infra\\conf\\geodata.go", "source_location": "L18"}, {"id": "conf_geodata_validatehttps", "label": "validateHTTPS()", "file_type": "code", "source_file": "C:\\Users\\Keanghour\\Documents\\GitHub\\FNode\\Rcon\\deps\\xray-core\\infra\\conf\\geodata.go", "source_location": "L31"}, {"id": "conf_geodataconfig", "label": "GeodataConfig", "file_type": "code", "source_file": "C:\\Users\\Keanghour\\Documents\\GitHub\\FNode\\Rcon\\deps\\xray-core\\infra\\conf\\geodata.go", "source_location": "L42"}, {"id": "conf_geodataconfig_build", "label": ".Build()", "file_type": "code", "source_file": "C:\\Users\\Keanghour\\Documents\\GitHub\\FNode\\Rcon\\deps\\xray-core\\infra\\conf\\geodata.go", "source_location": "L48"}], "edges": [{"source": "c_users_keanghour_documents_github_fnode_rcon_deps_xray_core_infra_conf_geodata_go", "target": "go_pkg_net_url", "relation": "imports_from", "confidence": "EXTRACTED", "source_file": "C:\\Users\\Keanghour\\Documents\\GitHub\\FNode\\Rcon\\deps\\xray-core\\infra\\conf\\geodata.go", "source_location": "L4", "weight": 1.0, "context": "import"}, {"source": "c_users_keanghour_documents_github_fnode_rcon_deps_xray_core_infra_conf_geodata_go", "target": "go_pkg_github_com_robfig_cron_v3", "relation": "imports_from", "confidence": "EXTRACTED", "source_file": "C:\\Users\\Keanghour\\Documents\\GitHub\\FNode\\Rcon\\deps\\xray-core\\infra\\conf\\geodata.go", "source_location": "L6", "weight": 1.0, "context": "import"}, {"source": "c_users_keanghour_documents_github_fnode_rcon_deps_xray_core_infra_conf_geodata_go", "target": "go_pkg_github_com_xtls_xray_core_app_geodata", "relation": "imports_from", "confidence": "EXTRACTED", "source_file": "C:\\Users\\Keanghour\\Documents\\GitHub\\FNode\\Rcon\\deps\\xray-core\\infra\\conf\\geodata.go", "source_location": "L7", "weight": 1.0, "context": "import"}, {"source": "c_users_keanghour_documents_github_fnode_rcon_deps_xray_core_infra_conf_geodata_go", "target": "go_pkg_github_com_xtls_xray_core_common_errors", "relation": "imports_from", "confidence": "EXTRACTED", "source_file": "C:\\Users\\Keanghour\\Documents\\GitHub\\FNode\\Rcon\\deps\\xray-core\\infra\\conf\\geodata.go", "source_location": "L8", "weight": 1.0, "context": "import"}, {"source": "c_users_keanghour_documents_github_fnode_rcon_deps_xray_core_infra_conf_geodata_go", "target": "go_pkg_github_com_xtls_xray_core_common_platform_filesystem", "relation": "imports_from", "confidence": "EXTRACTED", "source_file": "C:\\Users\\Keanghour\\Documents\\GitHub\\FNode\\Rcon\\deps\\xray-core\\infra\\conf\\geodata.go", "source_location": "L9", "weight": 1.0, "context": "import"}, {"source": "c_users_keanghour_documents_github_fnode_rcon_deps_xray_core_infra_conf_geodata_go", "target": "go_pkg_google_golang_org_protobuf_proto", "relation": "imports_from", "confidence": "EXTRACTED", "source_file": "C:\\Users\\Keanghour\\Documents\\GitHub\\FNode\\Rcon\\deps\\xray-core\\infra\\conf\\geodata.go", "source_location": "L10", "weight": 1.0, "context": "import"}, {"source": "c_users_keanghour_documents_github_fnode_rcon_deps_xray_core_infra_conf_geodata_go", "target": "conf_geodataassetconfig", "relation": "contains", "confidence": "EXTRACTED", "source_file": "C:\\Users\\Keanghour\\Documents\\GitHub\\FNode\\Rcon\\deps\\xray-core\\infra\\conf\\geodata.go", "source_location": "L13", "weight": 1.0}, {"source": "conf_geodataassetconfig", "target": "conf_geodataassetconfig_build", "relation": "method", "confidence": "EXTRACTED", "source_file": "C:\\Users\\Keanghour\\Documents\\GitHub\\FNode\\Rcon\\deps\\xray-core\\infra\\conf\\geodata.go", "source_location": "L18", "weight": 1.0}, {"source": "c_users_keanghour_documents_github_fnode_rcon_deps_xray_core_infra_conf_geodata_go", "target": "conf_geodata_validatehttps", "relation": "contains", "confidence": "EXTRACTED", "source_file": "C:\\Users\\Keanghour\\Documents\\GitHub\\FNode\\Rcon\\deps\\xray-core\\infra\\conf\\geodata.go", "source_location": "L31", "weight": 1.0}, {"source": "c_users_keanghour_documents_github_fnode_rcon_deps_xray_core_infra_conf_geodata_go", "target": "conf_geodataconfig", "relation": "contains", "confidence": "EXTRACTED", "source_file": "C:\\Users\\Keanghour\\Documents\\GitHub\\FNode\\Rcon\\deps\\xray-core\\infra\\conf\\geodata.go", "source_location": "L42", "weight": 1.0}, {"source": "conf_geodataconfig", "target": "conf_geodataconfig_build", "relation": "method", "confidence": "EXTRACTED", "source_file": "C:\\Users\\Keanghour\\Documents\\GitHub\\FNode\\Rcon\\deps\\xray-core\\infra\\conf\\geodata.go", "source_location": "L48", "weight": 1.0}, {"source": "conf_geodataassetconfig_build", "target": "conf_geodata_validatehttps", "relation": "calls", "context": "call", "confidence": "EXTRACTED", "source_file": "C:\\Users\\Keanghour\\Documents\\GitHub\\FNode\\Rcon\\deps\\xray-core\\infra\\conf\\geodata.go", "source_location": "L19", "weight": 1.0}], "raw_calls": [{"caller_nid": "conf_geodataassetconfig_build", "callee": "Base", "is_member_call": true, "source_file": "C:\\Users\\Keanghour\\Documents\\GitHub\\FNode\\Rcon\\deps\\xray-core\\infra\\conf\\geodata.go", "source_location": "L20"}, {"caller_nid": "conf_geodataassetconfig_build", "callee": "New", "is_member_call": false, "source_file": "C:\\Users\\Keanghour\\Documents\\GitHub\\FNode\\Rcon\\deps\\xray-core\\infra\\conf\\geodata.go", "source_location": "L20"}, {"caller_nid": "conf_geodataassetconfig_build", "callee": "StatAsset", "is_member_call": false, "source_file": "C:\\Users\\Keanghour\\Documents\\GitHub\\FNode\\Rcon\\deps\\xray-core\\infra\\conf\\geodata.go", "source_location": "L22"}, {"caller_nid": "conf_geodataassetconfig_build", "callee": "Base", "is_member_call": true, "source_file": "C:\\Users\\Keanghour\\Documents\\GitHub\\FNode\\Rcon\\deps\\xray-core\\infra\\conf\\geodata.go", "source_location": "L23"}, {"caller_nid": "conf_geodataassetconfig_build", "callee": "New", "is_member_call": false, "source_file": "C:\\Users\\Keanghour\\Documents\\GitHub\\FNode\\Rcon\\deps\\xray-core\\infra\\conf\\geodata.go", "source_location": "L23"}, {"caller_nid": "conf_geodata_validatehttps", "callee": "ParseRequestURI", "is_member_call": false, "source_file": "C:\\Users\\Keanghour\\Documents\\GitHub\\FNode\\Rcon\\deps\\xray-core\\infra\\conf\\geodata.go", "source_location": "L32"}, {"caller_nid": "conf_geodata_validatehttps", "callee": "New", "is_member_call": false, "source_file": "C:\\Users\\Keanghour\\Documents\\GitHub\\FNode\\Rcon\\deps\\xray-core\\infra\\conf\\geodata.go", "source_location": "L37"}, {"caller_nid": "conf_geodataconfig_build", "callee": "ParseStandard", "is_member_call": true, "source_file": "C:\\Users\\Keanghour\\Documents\\GitHub\\FNode\\Rcon\\deps\\xray-core\\infra\\conf\\geodata.go", "source_location": "L52"}, {"caller_nid": "conf_geodataconfig_build", "callee": "Base", "is_member_call": true, "source_file": "C:\\Users\\Keanghour\\Documents\\GitHub\\FNode\\Rcon\\deps\\xray-core\\infra\\conf\\geodata.go", "source_location": "L53"}, {"caller_nid": "conf_geodataconfig_build", "callee": "New", "is_member_call": false, "source_file": "C:\\Users\\Keanghour\\Documents\\GitHub\\FNode\\Rcon\\deps\\xray-core\\infra\\conf\\geodata.go", "source_location": "L53"}, {"caller_nid": "conf_geodataconfig_build", "callee": "make", "is_member_call": false, "source_file": "C:\\Users\\Keanghour\\Documents\\GitHub\\FNode\\Rcon\\deps\\xray-core\\infra\\conf\\geodata.go", "source_location": "L60"}, {"caller_nid": "conf_geodataconfig_build", "callee": "len", "is_member_call": false, "source_file": "C:\\Users\\Keanghour\\Documents\\GitHub\\FNode\\Rcon\\deps\\xray-core\\infra\\conf\\geodata.go", "source_location": "L60"}, {"caller_nid": "conf_geodataconfig_build", "callee": "Build", "is_member_call": true, "source_file": "C:\\Users\\Keanghour\\Documents\\GitHub\\FNode\\Rcon\\deps\\xray-core\\infra\\conf\\geodata.go", "source_location": "L62"}, {"caller_nid": "conf_geodataconfig_build", "callee": "append", "is_member_call": false, "source_file": "C:\\Users\\Keanghour\\Documents\\GitHub\\FNode\\Rcon\\deps\\xray-core\\infra\\conf\\geodata.go", "source_location": "L66"}]}