{"nodes": [{"id": "c_users_keanghour_documents_github_fnode_rcon_conf_conf_test_go", "label": "conf_test.go", "file_type": "code", "source_file": "C:\\Users\\Keanghour\\Documents\\GitHub\\FNode\\Rcon\\conf\\conf_test.go", "source_location": "L1"}, {"id": "conf_conf_test_testconf_loadfrompath", "label": "TestConf_LoadFromPath()", "file_type": "code", "source_file": "C:\\Users\\Keanghour\\Documents\\GitHub\\FNode\\Rcon\\conf\\conf_test.go", "source_location": "L7"}, {"id": "conf_conf_test_testconf_watch", "label": "TestConf_Watch()", "file_type": "code", "source_file": "C:\\Users\\Keanghour\\Documents\\GitHub\\FNode\\Rcon\\conf\\conf_test.go", "source_location": "L12"}], "edges": [{"source": "c_users_keanghour_documents_github_fnode_rcon_conf_conf_test_go", "target": "go_pkg_testing", "relation": "imports_from", "confidence": "EXTRACTED", "source_file": "C:\\Users\\Keanghour\\Documents\\GitHub\\FNode\\Rcon\\conf\\conf_test.go", "source_location": "L4", "weight": 1.0, "context": "import"}, {"source": "c_users_keanghour_documents_github_fnode_rcon_conf_conf_test_go", "target": "conf_conf_test_testconf_loadfrompath", "relation": "contains", "confidence": "EXTRACTED", "source_file": "C:\\Users\\Keanghour\\Documents\\GitHub\\FNode\\Rcon\\conf\\conf_test.go", "source_location": "L7", "weight": 1.0}, {"source": "c_users_keanghour_documents_github_fnode_rcon_conf_conf_test_go", "target": "conf_conf_test_testconf_watch", "relation": "contains", "confidence": "EXTRACTED", "source_file": "C:\\Users\\Keanghour\\Documents\\GitHub\\FNode\\Rcon\\conf\\conf_test.go", "source_location": "L12", "weight": 1.0}], "raw_calls": [{"caller_nid": "conf_conf_test_testconf_loadfrompath", "callee": "New", "is_member_call": false, "source_file": "C:\\Users\\Keanghour\\Documents\\GitHub\\FNode\\Rcon\\conf\\conf_test.go", "source_location": "L8"}, {"caller_nid": "conf_conf_test_testconf_loadfrompath", "callee": "Log", "is_member_call": true, "source_file": "C:\\Users\\Keanghour\\Documents\\GitHub\\FNode\\Rcon\\conf\\conf_test.go", "source_location": "L9"}, {"caller_nid": "conf_conf_test_testconf_loadfrompath", "callee": "LoadFromPath", "is_member_call": true, "source_file": "C:\\Users\\Keanghour\\Documents\\GitHub\\FNode\\Rcon\\conf\\conf_test.go", "source_location": "L9"}, {"caller_nid": "conf_conf_test_testconf_watch", "callee": "New", "is_member_call": false, "source_file": "C:\\Users\\Keanghour\\Documents\\GitHub\\FNode\\Rcon\\conf\\conf_test.go", "source_location": "L13"}, {"caller_nid": "conf_conf_test_testconf_watch", "callee": "Log", "is_member_call": true, "source_file": "C:\\Users\\Keanghour\\Documents\\GitHub\\FNode\\Rcon\\conf\\conf_test.go", "source_location": "L14"}, {"caller_nid": "conf_conf_test_testconf_watch", "callee": "Watch", "is_member_call": true, "source_file": "C:\\Users\\Keanghour\\Documents\\GitHub\\FNode\\Rcon\\conf\\conf_test.go", "source_location": "L14"}]}