{"nodes": [{"id": "c_users_keanghour_documents_github_fnode_xboard_master_theme_ez_theme_src_utils_notification_js", "label": "notification.js", "file_type": "code", "source_file": "C:\\Users\\Keanghour\\Documents\\GitHub\\FNode\\Xboard-master\\theme\\EZ_THEME\\src\\utils\\notification.js", "source_location": "L1"}, {"id": "utils_notification_showtoast", "label": "showToast()", "file_type": "code", "source_file": "C:\\Users\\Keanghour\\Documents\\GitHub\\FNode\\Xboard-master\\theme\\EZ_THEME\\src\\utils\\notification.js", "source_location": "L7"}], "edges": [{"source": "c_users_keanghour_documents_github_fnode_xboard_master_theme_ez_theme_src_utils_notification_js", "target": "usetoast", "relation": "imports_from", "context": "import", "confidence": "EXTRACTED", "source_file": "C:\\Users\\Keanghour\\Documents\\GitHub\\FNode\\Xboard-master\\theme\\EZ_THEME\\src\\utils\\notification.js", "source_location": "L2", "weight": 1.0}, {"source": "c_users_keanghour_documents_github_fnode_xboard_master_theme_ez_theme_src_utils_notification_js", "target": "utils_notification_showtoast", "relation": "contains", "confidence": "EXTRACTED", "source_file": "C:\\Users\\Keanghour\\Documents\\GitHub\\FNode\\Xboard-master\\theme\\EZ_THEME\\src\\utils\\notification.js", "source_location": "L7", "weight": 1.0}], "raw_calls": [{"caller_nid": "utils_notification_showtoast", "callee": "useToast", "is_member_call": false, "source_file": "C:\\Users\\Keanghour\\Documents\\GitHub\\FNode\\Xboard-master\\theme\\EZ_THEME\\src\\utils\\notification.js", "source_location": "L21"}, {"caller_nid": "utils_notification_showtoast", "callee": "createToast", "is_member_call": false, "source_file": "C:\\Users\\Keanghour\\Documents\\GitHub\\FNode\\Xboard-master\\theme\\EZ_THEME\\src\\utils\\notification.js", "source_location": "L22"}]}