{"nodes": [{"id": "c_users_keanghour_documents_github_fnode_xboard_master_app_models_giftcardcode_php", "label": "GiftCardCode.php", "file_type": "code", "source_file": "C:\\Users\\Keanghour\\Documents\\GitHub\\FNode\\Xboard-master\\app\\Models\\GiftCardCode.php", "source_location": "L1"}, {"id": "models_giftcardcode_giftcardcode", "label": "GiftCardCode", "file_type": "code", "source_file": "C:\\Users\\Keanghour\\Documents\\GitHub\\FNode\\Xboard-master\\app\\Models\\GiftCardCode.php", "source_location": "L28"}, {"id": "models_giftcardcode_giftcardcode_getstatusmap", "label": ".getStatusMap()", "file_type": "code", "source_file": "C:\\Users\\Keanghour\\Documents\\GitHub\\FNode\\Xboard-master\\app\\Models\\GiftCardCode.php", "source_location": "L65"}, {"id": "models_giftcardcode_giftcardcode_getstatusnameattribute", "label": ".getStatusNameAttribute()", "file_type": "code", "source_file": "C:\\Users\\Keanghour\\Documents\\GitHub\\FNode\\Xboard-master\\app\\Models\\GiftCardCode.php", "source_location": "L78"}, {"id": "models_giftcardcode_giftcardcode_template", "label": ".template()", "file_type": "code", "source_file": "C:\\Users\\Keanghour\\Documents\\GitHub\\FNode\\Xboard-master\\app\\Models\\GiftCardCode.php", "source_location": "L86"}, {"id": "models_giftcardcode_giftcardcode_user", "label": ".user()", "file_type": "code", "source_file": "C:\\Users\\Keanghour\\Documents\\GitHub\\FNode\\Xboard-master\\app\\Models\\GiftCardCode.php", "source_location": "L94"}, {"id": "models_giftcardcode_giftcardcode_usages", "label": ".usages()", "file_type": "code", "source_file": "C:\\Users\\Keanghour\\Documents\\GitHub\\FNode\\Xboard-master\\app\\Models\\GiftCardCode.php", "source_location": "L102"}, {"id": "models_giftcardcode_giftcardcode_isavailable", "label": ".isAvailable()", "file_type": "code", "source_file": "C:\\Users\\Keanghour\\Documents\\GitHub\\FNode\\Xboard-master\\app\\Models\\GiftCardCode.php", "source_location": "L110"}, {"id": "models_giftcardcode_giftcardcode_isexpired", "label": ".isExpired()", "file_type": "code", "source_file": "C:\\Users\\Keanghour\\Documents\\GitHub\\FNode\\Xboard-master\\app\\Models\\GiftCardCode.php", "source_location": "L133"}, {"id": "models_giftcardcode_giftcardcode_markasused", "label": ".markAsUsed()", "file_type": "code", "source_file": "C:\\Users\\Keanghour\\Documents\\GitHub\\FNode\\Xboard-master\\app\\Models\\GiftCardCode.php", "source_location": "L141"}, {"id": "models_giftcardcode_giftcardcode_markasexpired", "label": ".markAsExpired()", "file_type": "code", "source_file": "C:\\Users\\Keanghour\\Documents\\GitHub\\FNode\\Xboard-master\\app\\Models\\GiftCardCode.php", "source_location": "L154"}, {"id": "models_giftcardcode_giftcardcode_markasdisabled", "label": ".markAsDisabled()", "file_type": "code", "source_file": "C:\\Users\\Keanghour\\Documents\\GitHub\\FNode\\Xboard-master\\app\\Models\\GiftCardCode.php", "source_location": "L163"}, {"id": "models_giftcardcode_giftcardcode_generatecode", "label": ".generateCode()", "file_type": "code", "source_file": "C:\\Users\\Keanghour\\Documents\\GitHub\\FNode\\Xboard-master\\app\\Models\\GiftCardCode.php", "source_location": "L172"}, {"id": "models_giftcardcode_giftcardcode_batchgenerate", "label": ".batchGenerate()", "file_type": "code", "source_file": "C:\\Users\\Keanghour\\Documents\\GitHub\\FNode\\Xboard-master\\app\\Models\\GiftCardCode.php", "source_location": "L185"}, {"id": "models_giftcardcode_giftcardcode_setactualrewards", "label": ".setActualRewards()", "file_type": "code", "source_file": "C:\\Users\\Keanghour\\Documents\\GitHub\\FNode\\Xboard-master\\app\\Models\\GiftCardCode.php", "source_location": "L214"}, {"id": "models_giftcardcode_giftcardcode_getactualrewards", "label": ".getActualRewards()", "file_type": "code", "source_file": "C:\\Users\\Keanghour\\Documents\\GitHub\\FNode\\Xboard-master\\app\\Models\\GiftCardCode.php", "source_location": "L223"}, {"id": "models_giftcardcode_giftcardcode_validatecodeformat", "label": ".validateCodeFormat()", "file_type": "code", "source_file": "C:\\Users\\Keanghour\\Documents\\GitHub\\FNode\\Xboard-master\\app\\Models\\GiftCardCode.php", "source_location": "L231"}, {"id": "models_giftcardcode_giftcardcode_getbybatchid", "label": ".getByBatchId()", "file_type": "code", "source_file": "C:\\Users\\Keanghour\\Documents\\GitHub\\FNode\\Xboard-master\\app\\Models\\GiftCardCode.php", "source_location": "L240"}, {"id": "models_giftcardcode_giftcardcode_cleanupexpired", "label": ".cleanupExpired()", "file_type": "code", "source_file": "C:\\Users\\Keanghour\\Documents\\GitHub\\FNode\\Xboard-master\\app\\Models\\GiftCardCode.php", "source_location": "L248"}], "edges": [{"source": "c_users_keanghour_documents_github_fnode_xboard_master_app_models_giftcardcode_php", "target": "model", "relation": "imports", "context": "import", "confidence": "EXTRACTED", "source_file": "C:\\Users\\Keanghour\\Documents\\GitHub\\FNode\\Xboard-master\\app\\Models\\GiftCardCode.php", "source_location": "L5", "weight": 1.0}, {"source": "c_users_keanghour_documents_github_fnode_xboard_master_app_models_giftcardcode_php", "target": "belongsto", "relation": "imports", "context": "import", "confidence": "EXTRACTED", "source_file": "C:\\Users\\Keanghour\\Documents\\GitHub\\FNode\\Xboard-master\\app\\Models\\GiftCardCode.php", "source_location": "L6", "weight": 1.0}, {"source": "c_users_keanghour_documents_github_fnode_xboard_master_app_models_giftcardcode_php", "target": "hasmany", "relation": "imports", "context": "import", "confidence": "EXTRACTED", "source_file": "C:\\Users\\Keanghour\\Documents\\GitHub\\FNode\\Xboard-master\\app\\Models\\GiftCardCode.php", "source_location": "L7", "weight": 1.0}, {"source": "c_users_keanghour_documents_github_fnode_xboard_master_app_models_giftcardcode_php", "target": "models_giftcardcode_giftcardcode", "relation": "contains", "confidence": "EXTRACTED", "source_file": "C:\\Users\\Keanghour\\Documents\\GitHub\\FNode\\Xboard-master\\app\\Models\\GiftCardCode.php", "source_location": "L28", "weight": 1.0}, {"source": "models_giftcardcode_giftcardcode", "target": "models_giftcardcode_giftcardcode_getstatusmap", "relation": "method", "confidence": "EXTRACTED", "source_file": "C:\\Users\\Keanghour\\Documents\\GitHub\\FNode\\Xboard-master\\app\\Models\\GiftCardCode.php", "source_location": "L65", "weight": 1.0}, {"source": "models_giftcardcode_giftcardcode", "target": "models_giftcardcode_giftcardcode_getstatusnameattribute", "relation": "method", "confidence": "EXTRACTED", "source_file": "C:\\Users\\Keanghour\\Documents\\GitHub\\FNode\\Xboard-master\\app\\Models\\GiftCardCode.php", "source_location": "L78", "weight": 1.0}, {"source": "models_giftcardcode_giftcardcode", "target": "models_giftcardcode_giftcardcode_template", "relation": "method", "confidence": "EXTRACTED", "source_file": "C:\\Users\\Keanghour\\Documents\\GitHub\\FNode\\Xboard-master\\app\\Models\\GiftCardCode.php", "source_location": "L86", "weight": 1.0}, {"source": "models_giftcardcode_giftcardcode", "target": "models_giftcardcode_giftcardcode_user", "relation": "method", "confidence": "EXTRACTED", "source_file": "C:\\Users\\Keanghour\\Documents\\GitHub\\FNode\\Xboard-master\\app\\Models\\GiftCardCode.php", "source_location": "L94", "weight": 1.0}, {"source": "models_giftcardcode_giftcardcode", "target": "models_giftcardcode_giftcardcode_usages", "relation": "method", "confidence": "EXTRACTED", "source_file": "C:\\Users\\Keanghour\\Documents\\GitHub\\FNode\\Xboard-master\\app\\Models\\GiftCardCode.php", "source_location": "L102", "weight": 1.0}, {"source": "models_giftcardcode_giftcardcode", "target": "models_giftcardcode_giftcardcode_isavailable", "relation": "method", "confidence": "EXTRACTED", "source_file": "C:\\Users\\Keanghour\\Documents\\GitHub\\FNode\\Xboard-master\\app\\Models\\GiftCardCode.php", "source_location": "L110", "weight": 1.0}, {"source": "models_giftcardcode_giftcardcode", "target": "models_giftcardcode_giftcardcode_isexpired", "relation": "method", "confidence": "EXTRACTED", "source_file": "C:\\Users\\Keanghour\\Documents\\GitHub\\FNode\\Xboard-master\\app\\Models\\GiftCardCode.php", "source_location": "L133", "weight": 1.0}, {"source": "models_giftcardcode_giftcardcode", "target": "models_giftcardcode_giftcardcode_markasused", "relation": "method", "confidence": "EXTRACTED", "source_file": "C:\\Users\\Keanghour\\Documents\\GitHub\\FNode\\Xboard-master\\app\\Models\\GiftCardCode.php", "source_location": "L141", "weight": 1.0}, {"source": "models_giftcardcode_giftcardcode", "target": "models_giftcardcode_giftcardcode_markasexpired", "relation": "method", "confidence": "EXTRACTED", "source_file": "C:\\Users\\Keanghour\\Documents\\GitHub\\FNode\\Xboard-master\\app\\Models\\GiftCardCode.php", "source_location": "L154", "weight": 1.0}, {"source": "models_giftcardcode_giftcardcode", "target": "models_giftcardcode_giftcardcode_markasdisabled", "relation": "method", "confidence": "EXTRACTED", "source_file": "C:\\Users\\Keanghour\\Documents\\GitHub\\FNode\\Xboard-master\\app\\Models\\GiftCardCode.php", "source_location": "L163", "weight": 1.0}, {"source": "models_giftcardcode_giftcardcode", "target": "models_giftcardcode_giftcardcode_generatecode", "relation": "method", "confidence": "EXTRACTED", "source_file": "C:\\Users\\Keanghour\\Documents\\GitHub\\FNode\\Xboard-master\\app\\Models\\GiftCardCode.php", "source_location": "L172", "weight": 1.0}, {"source": "models_giftcardcode_giftcardcode", "target": "models_giftcardcode_giftcardcode_batchgenerate", "relation": "method", "confidence": "EXTRACTED", "source_file": "C:\\Users\\Keanghour\\Documents\\GitHub\\FNode\\Xboard-master\\app\\Models\\GiftCardCode.php", "source_location": "L185", "weight": 1.0}, {"source": "models_giftcardcode_giftcardcode", "target": "models_giftcardcode_giftcardcode_setactualrewards", "relation": "method", "confidence": "EXTRACTED", "source_file": "C:\\Users\\Keanghour\\Documents\\GitHub\\FNode\\Xboard-master\\app\\Models\\GiftCardCode.php", "source_location": "L214", "weight": 1.0}, {"source": "models_giftcardcode_giftcardcode", "target": "models_giftcardcode_giftcardcode_getactualrewards", "relation": "method", "confidence": "EXTRACTED", "source_file": "C:\\Users\\Keanghour\\Documents\\GitHub\\FNode\\Xboard-master\\app\\Models\\GiftCardCode.php", "source_location": "L223", "weight": 1.0}, {"source": "models_giftcardcode_giftcardcode", "target": "models_giftcardcode_giftcardcode_validatecodeformat", "relation": "method", "confidence": "EXTRACTED", "source_file": "C:\\Users\\Keanghour\\Documents\\GitHub\\FNode\\Xboard-master\\app\\Models\\GiftCardCode.php", "source_location": "L231", "weight": 1.0}, {"source": "models_giftcardcode_giftcardcode", "target": "models_giftcardcode_giftcardcode_getbybatchid", "relation": "method", "confidence": "EXTRACTED", "source_file": "C:\\Users\\Keanghour\\Documents\\GitHub\\FNode\\Xboard-master\\app\\Models\\GiftCardCode.php", "source_location": "L240", "weight": 1.0}, {"source": "models_giftcardcode_giftcardcode", "target": "models_giftcardcode_giftcardcode_cleanupexpired", "relation": "method", "confidence": "EXTRACTED", "source_file": "C:\\Users\\Keanghour\\Documents\\GitHub\\FNode\\Xboard-master\\app\\Models\\GiftCardCode.php", "source_location": "L248", "weight": 1.0}], "raw_calls": [{"caller_nid": "models_giftcardcode_giftcardcode_getstatusnameattribute", "callee": "self", "is_member_call": false, "source_file": "C:\\Users\\Keanghour\\Documents\\GitHub\\FNode\\Xboard-master\\app\\Models\\GiftCardCode.php", "source_location": "L80"}, {"caller_nid": "models_giftcardcode_giftcardcode_template", "callee": "belongsTo", "is_member_call": true, "source_file": "C:\\Users\\Keanghour\\Documents\\GitHub\\FNode\\Xboard-master\\app\\Models\\GiftCardCode.php", "source_location": "L88"}, {"caller_nid": "models_giftcardcode_giftcardcode_user", "callee": "belongsTo", "is_member_call": true, "source_file": "C:\\Users\\Keanghour\\Documents\\GitHub\\FNode\\Xboard-master\\app\\Models\\GiftCardCode.php", "source_location": "L96"}, {"caller_nid": "models_giftcardcode_giftcardcode_usages", "callee": "hasMany", "is_member_call": true, "source_file": "C:\\Users\\Keanghour\\Documents\\GitHub\\FNode\\Xboard-master\\app\\Models\\GiftCardCode.php", "source_location": "L104"}, {"caller_nid": "models_giftcardcode_giftcardcode_isavailable", "callee": "in_array", "is_member_call": false, "source_file": "C:\\Users\\Keanghour\\Documents\\GitHub\\FNode\\Xboard-master\\app\\Models\\GiftCardCode.php", "source_location": "L113"}, {"caller_nid": "models_giftcardcode_giftcardcode_isavailable", "callee": "time", "is_member_call": false, "source_file": "C:\\Users\\Keanghour\\Documents\\GitHub\\FNode\\Xboard-master\\app\\Models\\GiftCardCode.php", "source_location": "L118"}, {"caller_nid": "models_giftcardcode_giftcardcode_isexpired", "callee": "time", "is_member_call": false, "source_file": "C:\\Users\\Keanghour\\Documents\\GitHub\\FNode\\Xboard-master\\app\\Models\\GiftCardCode.php", "source_location": "L135"}, {"caller_nid": "models_giftcardcode_giftcardcode_markasused", "callee": "time", "is_member_call": false, "source_file": "C:\\Users\\Keanghour\\Documents\\GitHub\\FNode\\Xboard-master\\app\\Models\\GiftCardCode.php", "source_location": "L145"}, {"caller_nid": "models_giftcardcode_giftcardcode_markasused", "callee": "save", "is_member_call": true, "source_file": "C:\\Users\\Keanghour\\Documents\\GitHub\\FNode\\Xboard-master\\app\\Models\\GiftCardCode.php", "source_location": "L148"}, {"caller_nid": "models_giftcardcode_giftcardcode_markasexpired", "callee": "save", "is_member_call": true, "source_file": "C:\\Users\\Keanghour\\Documents\\GitHub\\FNode\\Xboard-master\\app\\Models\\GiftCardCode.php", "source_location": "L157"}, {"caller_nid": "models_giftcardcode_giftcardcode_markasdisabled", "callee": "save", "is_member_call": true, "source_file": "C:\\Users\\Keanghour\\Documents\\GitHub\\FNode\\Xboard-master\\app\\Models\\GiftCardCode.php", "source_location": "L166"}, {"caller_nid": "models_giftcardcode_giftcardcode_generatecode", "callee": "strtoupper", "is_member_call": false, "source_file": "C:\\Users\\Keanghour\\Documents\\GitHub\\FNode\\Xboard-master\\app\\Models\\GiftCardCode.php", "source_location": "L176"}, {"caller_nid": "models_giftcardcode_giftcardcode_generatecode", "callee": "substr", "is_member_call": false, "source_file": "C:\\Users\\Keanghour\\Documents\\GitHub\\FNode\\Xboard-master\\app\\Models\\GiftCardCode.php", "source_location": "L176"}, {"caller_nid": "models_giftcardcode_giftcardcode_generatecode", "callee": "md5", "is_member_call": false, "source_file": "C:\\Users\\Keanghour\\Documents\\GitHub\\FNode\\Xboard-master\\app\\Models\\GiftCardCode.php", "source_location": "L176"}, {"caller_nid": "models_giftcardcode_giftcardcode_generatecode", "callee": "uniqid", "is_member_call": false, "source_file": "C:\\Users\\Keanghour\\Documents\\GitHub\\FNode\\Xboard-master\\app\\Models\\GiftCardCode.php", "source_location": "L176"}, {"caller_nid": "models_giftcardcode_giftcardcode_generatecode", "callee": "mt_rand", "is_member_call": false, "source_file": "C:\\Users\\Keanghour\\Documents\\GitHub\\FNode\\Xboard-master\\app\\Models\\GiftCardCode.php", "source_location": "L176"}, {"caller_nid": "models_giftcardcode_giftcardcode_generatecode", "callee": "exists", "is_member_call": true, "source_file": "C:\\Users\\Keanghour\\Documents\\GitHub\\FNode\\Xboard-master\\app\\Models\\GiftCardCode.php", "source_location": "L177"}, {"caller_nid": "models_giftcardcode_giftcardcode_generatecode", "callee": "self", "is_member_call": false, "source_file": "C:\\Users\\Keanghour\\Documents\\GitHub\\FNode\\Xboard-master\\app\\Models\\GiftCardCode.php", "source_location": "L177"}, {"caller_nid": "models_giftcardcode_giftcardcode_batchgenerate", "callee": "uniqid", "is_member_call": false, "source_file": "C:\\Users\\Keanghour\\Documents\\GitHub\\FNode\\Xboard-master\\app\\Models\\GiftCardCode.php", "source_location": "L187"}, {"caller_nid": "models_giftcardcode_giftcardcode_batchgenerate", "callee": "self", "is_member_call": false, "source_file": "C:\\Users\\Keanghour\\Documents\\GitHub\\FNode\\Xboard-master\\app\\Models\\GiftCardCode.php", "source_location": "L196"}, {"caller_nid": "models_giftcardcode_giftcardcode_batchgenerate", "callee": "time", "is_member_call": false, "source_file": "C:\\Users\\Keanghour\\Documents\\GitHub\\FNode\\Xboard-master\\app\\Models\\GiftCardCode.php", "source_location": "L201"}, {"caller_nid": "models_giftcardcode_giftcardcode_batchgenerate", "callee": "time", "is_member_call": false, "source_file": "C:\\Users\\Keanghour\\Documents\\GitHub\\FNode\\Xboard-master\\app\\Models\\GiftCardCode.php", "source_location": "L202"}, {"caller_nid": "models_giftcardcode_giftcardcode_batchgenerate", "callee": "self", "is_member_call": false, "source_file": "C:\\Users\\Keanghour\\Documents\\GitHub\\FNode\\Xboard-master\\app\\Models\\GiftCardCode.php", "source_location": "L206"}, {"caller_nid": "models_giftcardcode_giftcardcode_setactualrewards", "callee": "save", "is_member_call": true, "source_file": "C:\\Users\\Keanghour\\Documents\\GitHub\\FNode\\Xboard-master\\app\\Models\\GiftCardCode.php", "source_location": "L217"}, {"caller_nid": "models_giftcardcode_giftcardcode_validatecodeformat", "callee": "preg_match", "is_member_call": false, "source_file": "C:\\Users\\Keanghour\\Documents\\GitHub\\FNode\\Xboard-master\\app\\Models\\GiftCardCode.php", "source_location": "L234"}, {"caller_nid": "models_giftcardcode_giftcardcode_getbybatchid", "callee": "get", "is_member_call": true, "source_file": "C:\\Users\\Keanghour\\Documents\\GitHub\\FNode\\Xboard-master\\app\\Models\\GiftCardCode.php", "source_location": "L242"}, {"caller_nid": "models_giftcardcode_giftcardcode_getbybatchid", "callee": "self", "is_member_call": false, "source_file": "C:\\Users\\Keanghour\\Documents\\GitHub\\FNode\\Xboard-master\\app\\Models\\GiftCardCode.php", "source_location": "L242"}, {"caller_nid": "models_giftcardcode_giftcardcode_cleanupexpired", "callee": "count", "is_member_call": true, "source_file": "C:\\Users\\Keanghour\\Documents\\GitHub\\FNode\\Xboard-master\\app\\Models\\GiftCardCode.php", "source_location": "L250"}, {"caller_nid": "models_giftcardcode_giftcardcode_cleanupexpired", "callee": "where", "is_member_call": true, "source_file": "C:\\Users\\Keanghour\\Documents\\GitHub\\FNode\\Xboard-master\\app\\Models\\GiftCardCode.php", "source_location": "L250"}, {"caller_nid": "models_giftcardcode_giftcardcode_cleanupexpired", "callee": "self", "is_member_call": false, "source_file": "C:\\Users\\Keanghour\\Documents\\GitHub\\FNode\\Xboard-master\\app\\Models\\GiftCardCode.php", "source_location": "L250"}, {"caller_nid": "models_giftcardcode_giftcardcode_cleanupexpired", "callee": "time", "is_member_call": false, "source_file": "C:\\Users\\Keanghour\\Documents\\GitHub\\FNode\\Xboard-master\\app\\Models\\GiftCardCode.php", "source_location": "L251"}, {"caller_nid": "models_giftcardcode_giftcardcode_cleanupexpired", "callee": "update", "is_member_call": true, "source_file": "C:\\Users\\Keanghour\\Documents\\GitHub\\FNode\\Xboard-master\\app\\Models\\GiftCardCode.php", "source_location": "L254"}, {"caller_nid": "models_giftcardcode_giftcardcode_cleanupexpired", "callee": "where", "is_member_call": true, "source_file": "C:\\Users\\Keanghour\\Documents\\GitHub\\FNode\\Xboard-master\\app\\Models\\GiftCardCode.php", "source_location": "L254"}, {"caller_nid": "models_giftcardcode_giftcardcode_cleanupexpired", "callee": "self", "is_member_call": false, "source_file": "C:\\Users\\Keanghour\\Documents\\GitHub\\FNode\\Xboard-master\\app\\Models\\GiftCardCode.php", "source_location": "L254"}, {"caller_nid": "models_giftcardcode_giftcardcode_cleanupexpired", "callee": "time", "is_member_call": false, "source_file": "C:\\Users\\Keanghour\\Documents\\GitHub\\FNode\\Xboard-master\\app\\Models\\GiftCardCode.php", "source_location": "L255"}]}