{"nodes": [{"id": "c_users_keanghour_documents_github_fnode_xboard_master_app_http_requests_admin_orderfetch_php", "label": "OrderFetch.php", "file_type": "code", "source_file": "C:\\Users\\Keanghour\\Documents\\GitHub\\FNode\\Xboard-master\\app\\Http\\Requests\\Admin\\OrderFetch.php", "source_location": "L1"}, {"id": "admin_orderfetch_orderfetch", "label": "OrderFetch", "file_type": "code", "source_file": "C:\\Users\\Keanghour\\Documents\\GitHub\\FNode\\Xboard-master\\app\\Http\\Requests\\Admin\\OrderFetch.php", "source_location": "L7"}, {"id": "admin_orderfetch_orderfetch_rules", "label": ".rules()", "file_type": "code", "source_file": "C:\\Users\\Keanghour\\Documents\\GitHub\\FNode\\Xboard-master\\app\\Http\\Requests\\Admin\\OrderFetch.php", "source_location": "L14"}, {"id": "admin_orderfetch_orderfetch_messages", "label": ".messages()", "file_type": "code", "source_file": "C:\\Users\\Keanghour\\Documents\\GitHub\\FNode\\Xboard-master\\app\\Http\\Requests\\Admin\\OrderFetch.php", "source_location": "L23"}], "edges": [{"source": "c_users_keanghour_documents_github_fnode_xboard_master_app_http_requests_admin_orderfetch_php", "target": "formrequest", "relation": "imports", "context": "import", "confidence": "EXTRACTED", "source_file": "C:\\Users\\Keanghour\\Documents\\GitHub\\FNode\\Xboard-master\\app\\Http\\Requests\\Admin\\OrderFetch.php", "source_location": "L5", "weight": 1.0}, {"source": "c_users_keanghour_documents_github_fnode_xboard_master_app_http_requests_admin_orderfetch_php", "target": "admin_orderfetch_orderfetch", "relation": "contains", "confidence": "EXTRACTED", "source_file": "C:\\Users\\Keanghour\\Documents\\GitHub\\FNode\\Xboard-master\\app\\Http\\Requests\\Admin\\OrderFetch.php", "source_location": "L7", "weight": 1.0}, {"source": "admin_orderfetch_orderfetch", "target": "admin_orderfetch_orderfetch_rules", "relation": "method", "confidence": "EXTRACTED", "source_file": "C:\\Users\\Keanghour\\Documents\\GitHub\\FNode\\Xboard-master\\app\\Http\\Requests\\Admin\\OrderFetch.php", "source_location": "L14", "weight": 1.0}, {"source": "admin_orderfetch_orderfetch", "target": "admin_orderfetch_orderfetch_messages", "relation": "method", "confidence": "EXTRACTED", "source_file": "C:\\Users\\Keanghour\\Documents\\GitHub\\FNode\\Xboard-master\\app\\Http\\Requests\\Admin\\OrderFetch.php", "source_location": "L23", "weight": 1.0}], "raw_calls": []}