{"nodes": [{"id": "c_users_keanghour_documents_github_fnode_xboard_master_app_websocket_nodeworker_php", "label": "NodeWorker.php", "file_type": "code", "source_file": "C:\\Users\\Keanghour\\Documents\\GitHub\\FNode\\Xboard-master\\app\\WebSocket\\NodeWorker.php", "source_location": "L1"}, {"id": "websocket_nodeworker_nodeworker", "label": "NodeWorker", "file_type": "code", "source_file": "C:\\Users\\Keanghour\\Documents\\GitHub\\FNode\\Xboard-master\\app\\WebSocket\\NodeWorker.php", "source_location": "L16"}, {"id": "websocket_nodeworker_nodeworker_construct", "label": ".__construct()", "file_type": "code", "source_file": "C:\\Users\\Keanghour\\Documents\\GitHub\\FNode\\Xboard-master\\app\\WebSocket\\NodeWorker.php", "source_location": "L30"}, {"id": "websocket_nodeworker_nodeworker_run", "label": ".run()", "file_type": "code", "source_file": "C:\\Users\\Keanghour\\Documents\\GitHub\\FNode\\Xboard-master\\app\\WebSocket\\NodeWorker.php", "source_location": "L37"}, {"id": "websocket_nodeworker_nodeworker_setuplogging", "label": ".setupLogging()", "file_type": "code", "source_file": "C:\\Users\\Keanghour\\Documents\\GitHub\\FNode\\Xboard-master\\app\\WebSocket\\NodeWorker.php", "source_location": "L44"}, {"id": "websocket_nodeworker_nodeworker_setupcallbacks", "label": ".setupCallbacks()", "file_type": "code", "source_file": "C:\\Users\\Keanghour\\Documents\\GitHub\\FNode\\Xboard-master\\app\\WebSocket\\NodeWorker.php", "source_location": "L54"}, {"id": "websocket_nodeworker_nodeworker_onworkerstart", "label": ".onWorkerStart()", "file_type": "code", "source_file": "C:\\Users\\Keanghour\\Documents\\GitHub\\FNode\\Xboard-master\\app\\WebSocket\\NodeWorker.php", "source_location": "L63"}, {"id": "websocket_nodeworker_nodeworker_setuptimers", "label": ".setupTimers()", "file_type": "code", "source_file": "C:\\Users\\Keanghour\\Documents\\GitHub\\FNode\\Xboard-master\\app\\WebSocket\\NodeWorker.php", "source_location": "L70"}, {"id": "websocket_nodeworker_nodeworker_onconnect", "label": ".onConnect()", "file_type": "code", "source_file": "C:\\Users\\Keanghour\\Documents\\GitHub\\FNode\\Xboard-master\\app\\WebSocket\\NodeWorker.php", "source_location": "L99"}, {"id": "websocket_nodeworker_nodeworker_onwebsocketconnect", "label": ".onWebSocketConnect()", "file_type": "code", "source_file": "C:\\Users\\Keanghour\\Documents\\GitHub\\FNode\\Xboard-master\\app\\WebSocket\\NodeWorker.php", "source_location": "L111"}, {"id": "websocket_nodeworker_nodeworker_onmessage", "label": ".onMessage()", "file_type": "code", "source_file": "C:\\Users\\Keanghour\\Documents\\GitHub\\FNode\\Xboard-master\\app\\WebSocket\\NodeWorker.php", "source_location": "L170"}, {"id": "websocket_nodeworker_nodeworker_onclose", "label": ".onClose()", "file_type": "code", "source_file": "C:\\Users\\Keanghour\\Documents\\GitHub\\FNode\\Xboard-master\\app\\WebSocket\\NodeWorker.php", "source_location": "L186"}, {"id": "websocket_nodeworker_nodeworker_subscriberedis", "label": ".subscribeRedis()", "file_type": "code", "source_file": "C:\\Users\\Keanghour\\Documents\\GitHub\\FNode\\Xboard-master\\app\\WebSocket\\NodeWorker.php", "source_location": "L206"}], "edges": [{"source": "c_users_keanghour_documents_github_fnode_xboard_master_app_websocket_nodeworker_php", "target": "server", "relation": "imports", "context": "import", "confidence": "EXTRACTED", "source_file": "C:\\Users\\Keanghour\\Documents\\GitHub\\FNode\\Xboard-master\\app\\WebSocket\\NodeWorker.php", "source_location": "L5", "weight": 1.0}, {"source": "c_users_keanghour_documents_github_fnode_xboard_master_app_websocket_nodeworker_php", "target": "devicestateservice", "relation": "imports", "context": "import", "confidence": "EXTRACTED", "source_file": "C:\\Users\\Keanghour\\Documents\\GitHub\\FNode\\Xboard-master\\app\\WebSocket\\NodeWorker.php", "source_location": "L6", "weight": 1.0}, {"source": "c_users_keanghour_documents_github_fnode_xboard_master_app_websocket_nodeworker_php", "target": "noderegistry", "relation": "imports", "context": "import", "confidence": "EXTRACTED", "source_file": "C:\\Users\\Keanghour\\Documents\\GitHub\\FNode\\Xboard-master\\app\\WebSocket\\NodeWorker.php", "source_location": "L7", "weight": 1.0}, {"source": "c_users_keanghour_documents_github_fnode_xboard_master_app_websocket_nodeworker_php", "target": "serverservice", "relation": "imports", "context": "import", "confidence": "EXTRACTED", "source_file": "C:\\Users\\Keanghour\\Documents\\GitHub\\FNode\\Xboard-master\\app\\WebSocket\\NodeWorker.php", "source_location": "L8", "weight": 1.0}, {"source": "c_users_keanghour_documents_github_fnode_xboard_master_app_websocket_nodeworker_php", "target": "cache", "relation": "imports", "context": "import", "confidence": "EXTRACTED", "source_file": "C:\\Users\\Keanghour\\Documents\\GitHub\\FNode\\Xboard-master\\app\\WebSocket\\NodeWorker.php", "source_location": "L9", "weight": 1.0}, {"source": "c_users_keanghour_documents_github_fnode_xboard_master_app_websocket_nodeworker_php", "target": "log", "relation": "imports", "context": "import", "confidence": "EXTRACTED", "source_file": "C:\\Users\\Keanghour\\Documents\\GitHub\\FNode\\Xboard-master\\app\\WebSocket\\NodeWorker.php", "source_location": "L10", "weight": 1.0}, {"source": "c_users_keanghour_documents_github_fnode_xboard_master_app_websocket_nodeworker_php", "target": "redis", "relation": "imports", "context": "import", "confidence": "EXTRACTED", "source_file": "C:\\Users\\Keanghour\\Documents\\GitHub\\FNode\\Xboard-master\\app\\WebSocket\\NodeWorker.php", "source_location": "L11", "weight": 1.0}, {"source": "c_users_keanghour_documents_github_fnode_xboard_master_app_websocket_nodeworker_php", "target": "tcpconnection", "relation": "imports", "context": "import", "confidence": "EXTRACTED", "source_file": "C:\\Users\\Keanghour\\Documents\\GitHub\\FNode\\Xboard-master\\app\\WebSocket\\NodeWorker.php", "source_location": "L12", "weight": 1.0}, {"source": "c_users_keanghour_documents_github_fnode_xboard_master_app_websocket_nodeworker_php", "target": "timer", "relation": "imports", "context": "import", "confidence": "EXTRACTED", "source_file": "C:\\Users\\Keanghour\\Documents\\GitHub\\FNode\\Xboard-master\\app\\WebSocket\\NodeWorker.php", "source_location": "L13", "weight": 1.0}, {"source": "c_users_keanghour_documents_github_fnode_xboard_master_app_websocket_nodeworker_php", "target": "worker", "relation": "imports", "context": "import", "confidence": "EXTRACTED", "source_file": "C:\\Users\\Keanghour\\Documents\\GitHub\\FNode\\Xboard-master\\app\\WebSocket\\NodeWorker.php", "source_location": "L14", "weight": 1.0}, {"source": "c_users_keanghour_documents_github_fnode_xboard_master_app_websocket_nodeworker_php", "target": "websocket_nodeworker_nodeworker", "relation": "contains", "confidence": "EXTRACTED", "source_file": "C:\\Users\\Keanghour\\Documents\\GitHub\\FNode\\Xboard-master\\app\\WebSocket\\NodeWorker.php", "source_location": "L16", "weight": 1.0}, {"source": "websocket_nodeworker_nodeworker", "target": "websocket_nodeworker_nodeworker_construct", "relation": "method", "confidence": "EXTRACTED", "source_file": "C:\\Users\\Keanghour\\Documents\\GitHub\\FNode\\Xboard-master\\app\\WebSocket\\NodeWorker.php", "source_location": "L30", "weight": 1.0}, {"source": "websocket_nodeworker_nodeworker", "target": "websocket_nodeworker_nodeworker_run", "relation": "method", "confidence": "EXTRACTED", "source_file": "C:\\Users\\Keanghour\\Documents\\GitHub\\FNode\\Xboard-master\\app\\WebSocket\\NodeWorker.php", "source_location": "L37", "weight": 1.0}, {"source": "websocket_nodeworker_nodeworker", "target": "websocket_nodeworker_nodeworker_setuplogging", "relation": "method", "confidence": "EXTRACTED", "source_file": "C:\\Users\\Keanghour\\Documents\\GitHub\\FNode\\Xboard-master\\app\\WebSocket\\NodeWorker.php", "source_location": "L44", "weight": 1.0}, {"source": "websocket_nodeworker_nodeworker", "target": "websocket_nodeworker_nodeworker_setupcallbacks", "relation": "method", "confidence": "EXTRACTED", "source_file": "C:\\Users\\Keanghour\\Documents\\GitHub\\FNode\\Xboard-master\\app\\WebSocket\\NodeWorker.php", "source_location": "L54", "weight": 1.0}, {"source": "websocket_nodeworker_nodeworker", "target": "websocket_nodeworker_nodeworker_onworkerstart", "relation": "method", "confidence": "EXTRACTED", "source_file": "C:\\Users\\Keanghour\\Documents\\GitHub\\FNode\\Xboard-master\\app\\WebSocket\\NodeWorker.php", "source_location": "L63", "weight": 1.0}, {"source": "websocket_nodeworker_nodeworker", "target": "websocket_nodeworker_nodeworker_setuptimers", "relation": "method", "confidence": "EXTRACTED", "source_file": "C:\\Users\\Keanghour\\Documents\\GitHub\\FNode\\Xboard-master\\app\\WebSocket\\NodeWorker.php", "source_location": "L70", "weight": 1.0}, {"source": "websocket_nodeworker_nodeworker", "target": "websocket_nodeworker_nodeworker_onconnect", "relation": "method", "confidence": "EXTRACTED", "source_file": "C:\\Users\\Keanghour\\Documents\\GitHub\\FNode\\Xboard-master\\app\\WebSocket\\NodeWorker.php", "source_location": "L99", "weight": 1.0}, {"source": "websocket_nodeworker_nodeworker", "target": "websocket_nodeworker_nodeworker_onwebsocketconnect", "relation": "method", "confidence": "EXTRACTED", "source_file": "C:\\Users\\Keanghour\\Documents\\GitHub\\FNode\\Xboard-master\\app\\WebSocket\\NodeWorker.php", "source_location": "L111", "weight": 1.0}, {"source": "websocket_nodeworker_nodeworker", "target": "websocket_nodeworker_nodeworker_onmessage", "relation": "method", "confidence": "EXTRACTED", "source_file": "C:\\Users\\Keanghour\\Documents\\GitHub\\FNode\\Xboard-master\\app\\WebSocket\\NodeWorker.php", "source_location": "L170", "weight": 1.0}, {"source": "websocket_nodeworker_nodeworker", "target": "websocket_nodeworker_nodeworker_onclose", "relation": "method", "confidence": "EXTRACTED", "source_file": "C:\\Users\\Keanghour\\Documents\\GitHub\\FNode\\Xboard-master\\app\\WebSocket\\NodeWorker.php", "source_location": "L186", "weight": 1.0}, {"source": "websocket_nodeworker_nodeworker", "target": "websocket_nodeworker_nodeworker_subscriberedis", "relation": "method", "confidence": "EXTRACTED", "source_file": "C:\\Users\\Keanghour\\Documents\\GitHub\\FNode\\Xboard-master\\app\\WebSocket\\NodeWorker.php", "source_location": "L206", "weight": 1.0}, {"source": "websocket_nodeworker_nodeworker_run", "target": "websocket_nodeworker_nodeworker_setuplogging", "relation": "calls", "context": "call", "confidence": "EXTRACTED", "source_file": "C:\\Users\\Keanghour\\Documents\\GitHub\\FNode\\Xboard-master\\app\\WebSocket\\NodeWorker.php", "source_location": "L39", "weight": 1.0}, {"source": "websocket_nodeworker_nodeworker_run", "target": "websocket_nodeworker_nodeworker_setupcallbacks", "relation": "calls", "context": "call", "confidence": "EXTRACTED", "source_file": "C:\\Users\\Keanghour\\Documents\\GitHub\\FNode\\Xboard-master\\app\\WebSocket\\NodeWorker.php", "source_location": "L40", "weight": 1.0}, {"source": "websocket_nodeworker_nodeworker_onworkerstart", "target": "websocket_nodeworker_nodeworker_subscriberedis", "relation": "calls", "context": "call", "confidence": "EXTRACTED", "source_file": "C:\\Users\\Keanghour\\Documents\\GitHub\\FNode\\Xboard-master\\app\\WebSocket\\NodeWorker.php", "source_location": "L66", "weight": 1.0}, {"source": "websocket_nodeworker_nodeworker_onworkerstart", "target": "websocket_nodeworker_nodeworker_setuptimers", "relation": "calls", "context": "call", "confidence": "EXTRACTED", "source_file": "C:\\Users\\Keanghour\\Documents\\GitHub\\FNode\\Xboard-master\\app\\WebSocket\\NodeWorker.php", "source_location": "L67", "weight": 1.0}], "raw_calls": [{"caller_nid": "websocket_nodeworker_nodeworker_run", "callee": "Worker", "is_member_call": false, "source_file": "C:\\Users\\Keanghour\\Documents\\GitHub\\FNode\\Xboard-master\\app\\WebSocket\\NodeWorker.php", "source_location": "L41"}, {"caller_nid": "websocket_nodeworker_nodeworker_setuplogging", "callee": "storage_path", "is_member_call": false, "source_file": "C:\\Users\\Keanghour\\Documents\\GitHub\\FNode\\Xboard-master\\app\\WebSocket\\NodeWorker.php", "source_location": "L46"}, {"caller_nid": "websocket_nodeworker_nodeworker_setuplogging", "callee": "is_dir", "is_member_call": false, "source_file": "C:\\Users\\Keanghour\\Documents\\GitHub\\FNode\\Xboard-master\\app\\WebSocket\\NodeWorker.php", "source_location": "L47"}, {"caller_nid": "websocket_nodeworker_nodeworker_setuplogging", "callee": "mkdir", "is_member_call": false, "source_file": "C:\\Users\\Keanghour\\Documents\\GitHub\\FNode\\Xboard-master\\app\\WebSocket\\NodeWorker.php", "source_location": "L48"}, {"caller_nid": "websocket_nodeworker_nodeworker_onworkerstart", "callee": "Log", "is_member_call": false, "source_file": "C:\\Users\\Keanghour\\Documents\\GitHub\\FNode\\Xboard-master\\app\\WebSocket\\NodeWorker.php", "source_location": "L65"}, {"caller_nid": "websocket_nodeworker_nodeworker_setuptimers", "callee": "Timer", "is_member_call": false, "source_file": "C:\\Users\\Keanghour\\Documents\\GitHub\\FNode\\Xboard-master\\app\\WebSocket\\NodeWorker.php", "source_location": "L73"}, {"caller_nid": "websocket_nodeworker_nodeworker_setuptimers", "callee": "NodeRegistry", "is_member_call": false, "source_file": "C:\\Users\\Keanghour\\Documents\\GitHub\\FNode\\Xboard-master\\app\\WebSocket\\NodeWorker.php", "source_location": "L74"}, {"caller_nid": "websocket_nodeworker_nodeworker_setuptimers", "callee": "NodeRegistry", "is_member_call": false, "source_file": "C:\\Users\\Keanghour\\Documents\\GitHub\\FNode\\Xboard-master\\app\\WebSocket\\NodeWorker.php", "source_location": "L75"}, {"caller_nid": "websocket_nodeworker_nodeworker_setuptimers", "callee": "send", "is_member_call": true, "source_file": "C:\\Users\\Keanghour\\Documents\\GitHub\\FNode\\Xboard-master\\app\\WebSocket\\NodeWorker.php", "source_location": "L77"}, {"caller_nid": "websocket_nodeworker_nodeworker_setuptimers", "callee": "json_encode", "is_member_call": false, "source_file": "C:\\Users\\Keanghour\\Documents\\GitHub\\FNode\\Xboard-master\\app\\WebSocket\\NodeWorker.php", "source_location": "L77"}, {"caller_nid": "websocket_nodeworker_nodeworker_setuptimers", "callee": "Timer", "is_member_call": false, "source_file": "C:\\Users\\Keanghour\\Documents\\GitHub\\FNode\\Xboard-master\\app\\WebSocket\\NodeWorker.php", "source_location": "L83"}, {"caller_nid": "websocket_nodeworker_nodeworker_setuptimers", "callee": "Redis", "is_member_call": false, "source_file": "C:\\Users\\Keanghour\\Documents\\GitHub\\FNode\\Xboard-master\\app\\WebSocket\\NodeWorker.php", "source_location": "L84"}, {"caller_nid": "websocket_nodeworker_nodeworker_setuptimers", "callee": "empty", "is_member_call": false, "source_file": "C:\\Users\\Keanghour\\Documents\\GitHub\\FNode\\Xboard-master\\app\\WebSocket\\NodeWorker.php", "source_location": "L85"}, {"caller_nid": "websocket_nodeworker_nodeworker_setuptimers", "callee": "app", "is_member_call": false, "source_file": "C:\\Users\\Keanghour\\Documents\\GitHub\\FNode\\Xboard-master\\app\\WebSocket\\NodeWorker.php", "source_location": "L89"}, {"caller_nid": "websocket_nodeworker_nodeworker_setuptimers", "callee": "NodeRegistry", "is_member_call": false, "source_file": "C:\\Users\\Keanghour\\Documents\\GitHub\\FNode\\Xboard-master\\app\\WebSocket\\NodeWorker.php", "source_location": "L92"}, {"caller_nid": "websocket_nodeworker_nodeworker_setuptimers", "callee": "NodeEventHandlers", "is_member_call": false, "source_file": "C:\\Users\\Keanghour\\Documents\\GitHub\\FNode\\Xboard-master\\app\\WebSocket\\NodeWorker.php", "source_location": "L93"}, {"caller_nid": "websocket_nodeworker_nodeworker_onconnect", "callee": "Timer", "is_member_call": false, "source_file": "C:\\Users\\Keanghour\\Documents\\GitHub\\FNode\\Xboard-master\\app\\WebSocket\\NodeWorker.php", "source_location": "L101"}, {"caller_nid": "websocket_nodeworker_nodeworker_onconnect", "callee": "empty", "is_member_call": false, "source_file": "C:\\Users\\Keanghour\\Documents\\GitHub\\FNode\\Xboard-master\\app\\WebSocket\\NodeWorker.php", "source_location": "L102"}, {"caller_nid": "websocket_nodeworker_nodeworker_onconnect", "callee": "close", "is_member_call": true, "source_file": "C:\\Users\\Keanghour\\Documents\\GitHub\\FNode\\Xboard-master\\app\\WebSocket\\NodeWorker.php", "source_location": "L103"}, {"caller_nid": "websocket_nodeworker_nodeworker_onconnect", "callee": "json_encode", "is_member_call": false, "source_file": "C:\\Users\\Keanghour\\Documents\\GitHub\\FNode\\Xboard-master\\app\\WebSocket\\NodeWorker.php", "source_location": "L103"}, {"caller_nid": "websocket_nodeworker_nodeworker_onwebsocketconnect", "callee": "is_string", "is_member_call": false, "source_file": "C:\\Users\\Keanghour\\Documents\\GitHub\\FNode\\Xboard-master\\app\\WebSocket\\NodeWorker.php", "source_location": "L114"}, {"caller_nid": "websocket_nodeworker_nodeworker_onwebsocketconnect", "callee": "parse_url", "is_member_call": false, "source_file": "C:\\Users\\Keanghour\\Documents\\GitHub\\FNode\\Xboard-master\\app\\WebSocket\\NodeWorker.php", "source_location": "L115"}, {"caller_nid": "websocket_nodeworker_nodeworker_onwebsocketconnect", "callee": "queryString", "is_member_call": true, "source_file": "C:\\Users\\Keanghour\\Documents\\GitHub\\FNode\\Xboard-master\\app\\WebSocket\\NodeWorker.php", "source_location": "L117"}, {"caller_nid": "websocket_nodeworker_nodeworker_onwebsocketconnect", "callee": "parse_str", "is_member_call": false, "source_file": "C:\\Users\\Keanghour\\Documents\\GitHub\\FNode\\Xboard-master\\app\\WebSocket\\NodeWorker.php", "source_location": "L120"}, {"caller_nid": "websocket_nodeworker_nodeworker_onwebsocketconnect", "callee": "admin_setting", "is_member_call": false, "source_file": "C:\\Users\\Keanghour\\Documents\\GitHub\\FNode\\Xboard-master\\app\\WebSocket\\NodeWorker.php", "source_location": "L125"}, {"caller_nid": "websocket_nodeworker_nodeworker_onwebsocketconnect", "callee": "hash_equals", "is_member_call": false, "source_file": "C:\\Users\\Keanghour\\Documents\\GitHub\\FNode\\Xboard-master\\app\\WebSocket\\NodeWorker.php", "source_location": "L126"}, {"caller_nid": "websocket_nodeworker_nodeworker_onwebsocketconnect", "callee": "close", "is_member_call": true, "source_file": "C:\\Users\\Keanghour\\Documents\\GitHub\\FNode\\Xboard-master\\app\\WebSocket\\NodeWorker.php", "source_location": "L127"}, {"caller_nid": "websocket_nodeworker_nodeworker_onwebsocketconnect", "callee": "json_encode", "is_member_call": false, "source_file": "C:\\Users\\Keanghour\\Documents\\GitHub\\FNode\\Xboard-master\\app\\WebSocket\\NodeWorker.php", "source_location": "L127"}, {"caller_nid": "websocket_nodeworker_nodeworker_onwebsocketconnect", "callee": "ServerService", "is_member_call": false, "source_file": "C:\\Users\\Keanghour\\Documents\\GitHub\\FNode\\Xboard-master\\app\\WebSocket\\NodeWorker.php", "source_location": "L134"}, {"caller_nid": "websocket_nodeworker_nodeworker_onwebsocketconnect", "callee": "close", "is_member_call": true, "source_file": "C:\\Users\\Keanghour\\Documents\\GitHub\\FNode\\Xboard-master\\app\\WebSocket\\NodeWorker.php", "source_location": "L136"}, {"caller_nid": "websocket_nodeworker_nodeworker_onwebsocketconnect", "callee": "json_encode", "is_member_call": false, "source_file": "C:\\Users\\Keanghour\\Documents\\GitHub\\FNode\\Xboard-master\\app\\WebSocket\\NodeWorker.php", "source_location": "L136"}, {"caller_nid": "websocket_nodeworker_nodeworker_onwebsocketconnect", "callee": "isset", "is_member_call": false, "source_file": "C:\\Users\\Keanghour\\Documents\\GitHub\\FNode\\Xboard-master\\app\\WebSocket\\NodeWorker.php", "source_location": "L144"}, {"caller_nid": "websocket_nodeworker_nodeworker_onwebsocketconnect", "callee": "Timer", "is_member_call": false, "source_file": "C:\\Users\\Keanghour\\Documents\\GitHub\\FNode\\Xboard-master\\app\\WebSocket\\NodeWorker.php", "source_location": "L145"}, {"caller_nid": "websocket_nodeworker_nodeworker_onwebsocketconnect", "callee": "NodeRegistry", "is_member_call": false, "source_file": "C:\\Users\\Keanghour\\Documents\\GitHub\\FNode\\Xboard-master\\app\\WebSocket\\NodeWorker.php", "source_location": "L149"}, {"caller_nid": "websocket_nodeworker_nodeworker_onwebsocketconnect", "callee": "Cache", "is_member_call": false, "source_file": "C:\\Users\\Keanghour\\Documents\\GitHub\\FNode\\Xboard-master\\app\\WebSocket\\NodeWorker.php", "source_location": "L150"}, {"caller_nid": "websocket_nodeworker_nodeworker_onwebsocketconnect", "callee": "clearAllNodeDevices", "is_member_call": true, "source_file": "C:\\Users\\Keanghour\\Documents\\GitHub\\FNode\\Xboard-master\\app\\WebSocket\\NodeWorker.php", "source_location": "L153"}, {"caller_nid": "websocket_nodeworker_nodeworker_onwebsocketconnect", "callee": "app", "is_member_call": false, "source_file": "C:\\Users\\Keanghour\\Documents\\GitHub\\FNode\\Xboard-master\\app\\WebSocket\\NodeWorker.php", "source_location": "L153"}, {"caller_nid": "websocket_nodeworker_nodeworker_onwebsocketconnect", "callee": "Log", "is_member_call": false, "source_file": "C:\\Users\\Keanghour\\Documents\\GitHub\\FNode\\Xboard-master\\app\\WebSocket\\NodeWorker.php", "source_location": "L155"}, {"caller_nid": "websocket_nodeworker_nodeworker_onwebsocketconnect", "callee": "getRemoteIp", "is_member_call": true, "source_file": "C:\\Users\\Keanghour\\Documents\\GitHub\\FNode\\Xboard-master\\app\\WebSocket\\NodeWorker.php", "source_location": "L156"}, {"caller_nid": "websocket_nodeworker_nodeworker_onwebsocketconnect", "callee": "NodeRegistry", "is_member_call": false, "source_file": "C:\\Users\\Keanghour\\Documents\\GitHub\\FNode\\Xboard-master\\app\\WebSocket\\NodeWorker.php", "source_location": "L157"}, {"caller_nid": "websocket_nodeworker_nodeworker_onwebsocketconnect", "callee": "send", "is_member_call": true, "source_file": "C:\\Users\\Keanghour\\Documents\\GitHub\\FNode\\Xboard-master\\app\\WebSocket\\NodeWorker.php", "source_location": "L161"}, {"caller_nid": "websocket_nodeworker_nodeworker_onwebsocketconnect", "callee": "json_encode", "is_member_call": false, "source_file": "C:\\Users\\Keanghour\\Documents\\GitHub\\FNode\\Xboard-master\\app\\WebSocket\\NodeWorker.php", "source_location": "L161"}, {"caller_nid": "websocket_nodeworker_nodeworker_onwebsocketconnect", "callee": "NodeEventHandlers", "is_member_call": false, "source_file": "C:\\Users\\Keanghour\\Documents\\GitHub\\FNode\\Xboard-master\\app\\WebSocket\\NodeWorker.php", "source_location": "L167"}, {"caller_nid": "websocket_nodeworker_nodeworker_onmessage", "callee": "json_decode", "is_member_call": false, "source_file": "C:\\Users\\Keanghour\\Documents\\GitHub\\FNode\\Xboard-master\\app\\WebSocket\\NodeWorker.php", "source_location": "L172"}, {"caller_nid": "websocket_nodeworker_nodeworker_onmessage", "callee": "is_array", "is_member_call": false, "source_file": "C:\\Users\\Keanghour\\Documents\\GitHub\\FNode\\Xboard-master\\app\\WebSocket\\NodeWorker.php", "source_location": "L173"}, {"caller_nid": "websocket_nodeworker_nodeworker_onmessage", "callee": "isset", "is_member_call": false, "source_file": "C:\\Users\\Keanghour\\Documents\\GitHub\\FNode\\Xboard-master\\app\\WebSocket\\NodeWorker.php", "source_location": "L180"}, {"caller_nid": "websocket_nodeworker_nodeworker_onmessage", "callee": "$handler", "is_member_call": false, "source_file": "C:\\Users\\Keanghour\\Documents\\GitHub\\FNode\\Xboard-master\\app\\WebSocket\\NodeWorker.php", "source_location": "L182"}, {"caller_nid": "websocket_nodeworker_nodeworker_onclose", "callee": "empty", "is_member_call": false, "source_file": "C:\\Users\\Keanghour\\Documents\\GitHub\\FNode\\Xboard-master\\app\\WebSocket\\NodeWorker.php", "source_location": "L188"}, {"caller_nid": "websocket_nodeworker_nodeworker_onclose", "callee": "NodeRegistry", "is_member_call": false, "source_file": "C:\\Users\\Keanghour\\Documents\\GitHub\\FNode\\Xboard-master\\app\\WebSocket\\NodeWorker.php", "source_location": "L190"}, {"caller_nid": "websocket_nodeworker_nodeworker_onclose", "callee": "Cache", "is_member_call": false, "source_file": "C:\\Users\\Keanghour\\Documents\\GitHub\\FNode\\Xboard-master\\app\\WebSocket\\NodeWorker.php", "source_location": "L191"}, {"caller_nid": "websocket_nodeworker_nodeworker_onclose", "callee": "app", "is_member_call": false, "source_file": "C:\\Users\\Keanghour\\Documents\\GitHub\\FNode\\Xboard-master\\app\\WebSocket\\NodeWorker.php", "source_location": "L193"}, {"caller_nid": "websocket_nodeworker_nodeworker_onclose", "callee": "clearAllNodeDevices", "is_member_call": true, "source_file": "C:\\Users\\Keanghour\\Documents\\GitHub\\FNode\\Xboard-master\\app\\WebSocket\\NodeWorker.php", "source_location": "L194"}, {"caller_nid": "websocket_nodeworker_nodeworker_onclose", "callee": "notifyUpdate", "is_member_call": true, "source_file": "C:\\Users\\Keanghour\\Documents\\GitHub\\FNode\\Xboard-master\\app\\WebSocket\\NodeWorker.php", "source_location": "L196"}, {"caller_nid": "websocket_nodeworker_nodeworker_onclose", "callee": "Log", "is_member_call": false, "source_file": "C:\\Users\\Keanghour\\Documents\\GitHub\\FNode\\Xboard-master\\app\\WebSocket\\NodeWorker.php", "source_location": "L199"}, {"caller_nid": "websocket_nodeworker_nodeworker_onclose", "callee": "NodeRegistry", "is_member_call": false, "source_file": "C:\\Users\\Keanghour\\Documents\\GitHub\\FNode\\Xboard-master\\app\\WebSocket\\NodeWorker.php", "source_location": "L200"}, {"caller_nid": "websocket_nodeworker_nodeworker_onclose", "callee": "count", "is_member_call": false, "source_file": "C:\\Users\\Keanghour\\Documents\\GitHub\\FNode\\Xboard-master\\app\\WebSocket\\NodeWorker.php", "source_location": "L201"}, {"caller_nid": "websocket_nodeworker_nodeworker_subscriberedis", "callee": "config", "is_member_call": false, "source_file": "C:\\Users\\Keanghour\\Documents\\GitHub\\FNode\\Xboard-master\\app\\WebSocket\\NodeWorker.php", "source_location": "L208"}, {"caller_nid": "websocket_nodeworker_nodeworker_subscriberedis", "callee": "config", "is_member_call": false, "source_file": "C:\\Users\\Keanghour\\Documents\\GitHub\\FNode\\Xboard-master\\app\\WebSocket\\NodeWorker.php", "source_location": "L209"}, {"caller_nid": "websocket_nodeworker_nodeworker_subscriberedis", "callee": "str_starts_with", "is_member_call": false, "source_file": "C:\\Users\\Keanghour\\Documents\\GitHub\\FNode\\Xboard-master\\app\\WebSocket\\NodeWorker.php", "source_location": "L211"}, {"caller_nid": "websocket_nodeworker_nodeworker_subscriberedis", "callee": "config", "is_member_call": false, "source_file": "C:\\Users\\Keanghour\\Documents\\GitHub\\FNode\\Xboard-master\\app\\WebSocket\\NodeWorker.php", "source_location": "L219"}, {"caller_nid": "websocket_nodeworker_nodeworker_subscriberedis", "callee": "auth", "is_member_call": true, "source_file": "C:\\Users\\Keanghour\\Documents\\GitHub\\FNode\\Xboard-master\\app\\WebSocket\\NodeWorker.php", "source_location": "L221"}, {"caller_nid": "websocket_nodeworker_nodeworker_subscriberedis", "callee": "config", "is_member_call": false, "source_file": "C:\\Users\\Keanghour\\Documents\\GitHub\\FNode\\Xboard-master\\app\\WebSocket\\NodeWorker.php", "source_location": "L224"}, {"caller_nid": "websocket_nodeworker_nodeworker_subscriberedis", "callee": "subscribe", "is_member_call": true, "source_file": "C:\\Users\\Keanghour\\Documents\\GitHub\\FNode\\Xboard-master\\app\\WebSocket\\NodeWorker.php", "source_location": "L227"}, {"caller_nid": "websocket_nodeworker_nodeworker_subscriberedis", "callee": "json_decode", "is_member_call": false, "source_file": "C:\\Users\\Keanghour\\Documents\\GitHub\\FNode\\Xboard-master\\app\\WebSocket\\NodeWorker.php", "source_location": "L228"}, {"caller_nid": "websocket_nodeworker_nodeworker_subscriberedis", "callee": "is_array", "is_member_call": false, "source_file": "C:\\Users\\Keanghour\\Documents\\GitHub\\FNode\\Xboard-master\\app\\WebSocket\\NodeWorker.php", "source_location": "L229"}, {"caller_nid": "websocket_nodeworker_nodeworker_subscriberedis", "callee": "NodeRegistry", "is_member_call": false, "source_file": "C:\\Users\\Keanghour\\Documents\\GitHub\\FNode\\Xboard-master\\app\\WebSocket\\NodeWorker.php", "source_location": "L241"}, {"caller_nid": "websocket_nodeworker_nodeworker_subscriberedis", "callee": "Log", "is_member_call": false, "source_file": "C:\\Users\\Keanghour\\Documents\\GitHub\\FNode\\Xboard-master\\app\\WebSocket\\NodeWorker.php", "source_location": "L243"}, {"caller_nid": "websocket_nodeworker_nodeworker_subscriberedis", "callee": "Log", "is_member_call": false, "source_file": "C:\\Users\\Keanghour\\Documents\\GitHub\\FNode\\Xboard-master\\app\\WebSocket\\NodeWorker.php", "source_location": "L247"}]}